{
    "dependency_tree": {
        "__AUTOGENERATED_FILE_DO_NOT_MODIFY_THIS_FILE_MANUALLY": -1291503241,
        "conflict_resolution": {},
        "dependencies": [
            {
                "coord": "com.fasterxml.jackson.core:jackson-annotations:2.12.0",
                "dependencies": [],
                "directDependencies": [],
                "file": "v1/https/jcenter.bintray.com/com/fasterxml/jackson/core/jackson-annotations/2.12.0/jackson-annotations-2.12.0.jar",
                "mirror_urls": [
                    "https://jcenter.bintray.com/com/fasterxml/jackson/core/jackson-annotations/2.12.0/jackson-annotations-2.12.0.jar"
                ],
                "sha256": "c28fbe62e7be1e29df75953fa8a887ff875d4482291fbfddb1aec5c91191ecda",
                "url": "https://jcenter.bintray.com/com/fasterxml/jackson/core/jackson-annotations/2.12.0/jackson-annotations-2.12.0.jar"
            },
            {
                "coord": "com.fasterxml.jackson.core:jackson-core:2.12.0",
                "dependencies": [],
                "directDependencies": [],
                "file": "v1/https/jcenter.bintray.com/com/fasterxml/jackson/core/jackson-core/2.12.0/jackson-core-2.12.0.jar",
                "mirror_urls": [
                    "https://jcenter.bintray.com/com/fasterxml/jackson/core/jackson-core/2.12.0/jackson-core-2.12.0.jar"
                ],
                "sha256": "8acab5ef6e4f332bbb331b3fcd24d716598770d13a47e7215aa5ee625d1fd9c9",
                "url": "https://jcenter.bintray.com/com/fasterxml/jackson/core/jackson-core/2.12.0/jackson-core-2.12.0.jar"
            },
            {
                "coord": "com.fasterxml.jackson.core:jackson-databind:2.12.0",
                "dependencies": [
                    "com.fasterxml.jackson.core:jackson-annotations:2.12.0",
                    "com.fasterxml.jackson.core:jackson-core:2.12.0"
                ],
                "directDependencies": [
                    "com.fasterxml.jackson.core:jackson-annotations:2.12.0",
                    "com.fasterxml.jackson.core:jackson-core:2.12.0"
                ],
                "file": "v1/https/jcenter.bintray.com/com/fasterxml/jackson/core/jackson-databind/2.12.0/jackson-databind-2.12.0.jar",
                "mirror_urls": [
                    "https://jcenter.bintray.com/com/fasterxml/jackson/core/jackson-databind/2.12.0/jackson-databind-2.12.0.jar"
                ],
                "sha256": "75d470eda0dd559e43f2ad08209fa09ecd268833492ba93fa46f6f3607acbab7",
                "url": "https://jcenter.bintray.com/com/fasterxml/jackson/core/jackson-databind/2.12.0/jackson-databind-2.12.0.jar"
            },
            {
                "coord": "com.fasterxml.jackson.module:jackson-module-kotlin:2.12.0",
                "dependencies": [
                    "com.fasterxml.jackson.core:jackson-databind:2.12.0",
                    "com.fasterxml.jackson.core:jackson-annotations:2.12.0",
                    "org.jetbrains.kotlin:kotlin-reflect:1.4.21",
                    "com.fasterxml.jackson.core:jackson-core:2.12.0"
                ],
                "directDependencies": [
                    "com.fasterxml.jackson.core:jackson-annotations:2.12.0",
                    "com.fasterxml.jackson.core:jackson-databind:2.12.0",
                    "org.jetbrains.kotlin:kotlin-reflect:1.4.21"
                ],
                "file": "v1/https/jcenter.bintray.com/com/fasterxml/jackson/module/jackson-module-kotlin/2.12.0/jackson-module-kotlin-2.12.0.jar",
                "mirror_urls": [
                    "https://jcenter.bintray.com/com/fasterxml/jackson/module/jackson-module-kotlin/2.12.0/jackson-module-kotlin-2.12.0.jar"
                ],
                "sha256": "ee69650831f72ff2411026b507f3583e90ca88b40e9dae3067f87b34088e0ced",
                "url": "https://jcenter.bintray.com/com/fasterxml/jackson/module/jackson-module-kotlin/2.12.0/jackson-module-kotlin-2.12.0.jar"
            },
            {
                "coord": "com.google.code.findbugs:jsr305:3.0.2",
                "dependencies": [],
                "directDependencies": [],
                "file": "v1/https/jcenter.bintray.com/com/google/code/findbugs/jsr305/3.0.2/jsr305-3.0.2.jar",
                "mirror_urls": [
                    "https://jcenter.bintray.com/com/google/code/findbugs/jsr305/3.0.2/jsr305-3.0.2.jar"
                ],
                "sha256": "766ad2a0783f2687962c8ad74ceecc38a28b9f72a2d085ee438b7813e928d0c7",
                "url": "https://jcenter.bintray.com/com/google/code/findbugs/jsr305/3.0.2/jsr305-3.0.2.jar"
            },
            {
                "coord": "com.google.errorprone:error_prone_annotations:2.2.0",
                "dependencies": [],
                "directDependencies": [],
                "file": "v1/https/jcenter.bintray.com/com/google/errorprone/error_prone_annotations/2.2.0/error_prone_annotations-2.2.0.jar",
                "mirror_urls": [
                    "https://jcenter.bintray.com/com/google/errorprone/error_prone_annotations/2.2.0/error_prone_annotations-2.2.0.jar"
                ],
                "sha256": "6ebd22ca1b9d8ec06d41de8d64e0596981d9607b42035f9ed374f9de271a481a",
                "url": "https://jcenter.bintray.com/com/google/errorprone/error_prone_annotations/2.2.0/error_prone_annotations-2.2.0.jar"
            },
            {
                "coord": "com.google.guava:failureaccess:1.0",
                "dependencies": [],
                "directDependencies": [],
                "file": "v1/https/jcenter.bintray.com/com/google/guava/failureaccess/1.0/failureaccess-1.0.jar",
                "mirror_urls": [
                    "https://jcenter.bintray.com/com/google/guava/failureaccess/1.0/failureaccess-1.0.jar"
                ],
                "sha256": "d084bef9cd07a8537a1753e4850a69b7e8bab1d1e22e9f3a1e4826309a7a2336",
                "url": "https://jcenter.bintray.com/com/google/guava/failureaccess/1.0/failureaccess-1.0.jar"
            },
            {
                "coord": "com.google.guava:guava:27.0-jre",
                "dependencies": [
                    "com.google.guava:listenablefuture:9999.0-empty-to-avoid-conflict-with-guava",
                    "com.google.code.findbugs:jsr305:3.0.2",
                    "com.google.guava:failureaccess:1.0",
                    "org.codehaus.mojo:animal-sniffer-annotations:1.17",
                    "com.google.j2objc:j2objc-annotations:1.1",
                    "com.google.errorprone:error_prone_annotations:2.2.0",
                    "org.checkerframework:checker-qual:2.5.2"
                ],
                "directDependencies": [
                    "com.google.guava:listenablefuture:9999.0-empty-to-avoid-conflict-with-guava",
                    "com.google.code.findbugs:jsr305:3.0.2",
                    "com.google.guava:failureaccess:1.0",
                    "org.codehaus.mojo:animal-sniffer-annotations:1.17",
                    "com.google.j2objc:j2objc-annotations:1.1",
                    "com.google.errorprone:error_prone_annotations:2.2.0",
                    "org.checkerframework:checker-qual:2.5.2"
                ],
                "file": "v1/https/jcenter.bintray.com/com/google/guava/guava/27.0-jre/guava-27.0-jre.jar",
                "mirror_urls": [
                    "https://jcenter.bintray.com/com/google/guava/guava/27.0-jre/guava-27.0-jre.jar"
                ],
                "sha256": "63b09db6861011e7fb2481be7790c7fd4b03f0bb884b3de2ecba8823ad19bf3f",
                "url": "https://jcenter.bintray.com/com/google/guava/guava/27.0-jre/guava-27.0-jre.jar"
            },
            {
                "coord": "com.google.guava:listenablefuture:9999.0-empty-to-avoid-conflict-with-guava",
                "dependencies": [],
                "directDependencies": [],
                "file": "v1/https/jcenter.bintray.com/com/google/guava/listenablefuture/9999.0-empty-to-avoid-conflict-with-guava/listenablefuture-9999.0-empty-to-avoid-conflict-with-guava.jar",
                "mirror_urls": [
                    "https://jcenter.bintray.com/com/google/guava/listenablefuture/9999.0-empty-to-avoid-conflict-with-guava/listenablefuture-9999.0-empty-to-avoid-conflict-with-guava.jar"
                ],
                "sha256": "b372a037d4230aa57fbeffdef30fd6123f9c0c2db85d0aced00c91b974f33f99",
                "url": "https://jcenter.bintray.com/com/google/guava/listenablefuture/9999.0-empty-to-avoid-conflict-with-guava/listenablefuture-9999.0-empty-to-avoid-conflict-with-guava.jar"
            },
            {
                "coord": "com.google.j2objc:j2objc-annotations:1.1",
                "dependencies": [],
                "directDependencies": [],
                "file": "v1/https/jcenter.bintray.com/com/google/j2objc/j2objc-annotations/1.1/j2objc-annotations-1.1.jar",
                "mirror_urls": [
                    "https://jcenter.bintray.com/com/google/j2objc/j2objc-annotations/1.1/j2objc-annotations-1.1.jar"
                ],
                "sha256": "2994a7eb78f2710bd3d3bfb639b2c94e219cedac0d4d084d516e78c16dddecf6",
                "url": "https://jcenter.bintray.com/com/google/j2objc/j2objc-annotations/1.1/j2objc-annotations-1.1.jar"
            },
            {
                "coord": "commons-codec:commons-codec:1.13",
                "dependencies": [],
                "directDependencies": [],
                "file": "v1/https/jcenter.bintray.com/commons-codec/commons-codec/1.13/commons-codec-1.13.jar",
                "mirror_urls": [
                    "https://jcenter.bintray.com/commons-codec/commons-codec/1.13/commons-codec-1.13.jar"
                ],
                "sha256": "61f7a3079e92b9fdd605238d0295af5fd11ac411a0a0af48deace1f6c5ffa072",
                "url": "https://jcenter.bintray.com/commons-codec/commons-codec/1.13/commons-codec-1.13.jar"
            },
            {
                "coord": "org.apache.httpcomponents.client5:httpclient5:5.0.3",
                "dependencies": [
                    "commons-codec:commons-codec:1.13",
                    "org.slf4j:slf4j-api:1.7.25",
                    "org.apache.httpcomponents.core5:httpcore5-h2:5.0.2",
                    "org.apache.httpcomponents.core5:httpcore5:5.0.2"
                ],
                "directDependencies": [
                    "commons-codec:commons-codec:1.13",
                    "org.apache.httpcomponents.core5:httpcore5:5.0.2",
                    "org.apache.httpcomponents.core5:httpcore5-h2:5.0.2",
                    "org.slf4j:slf4j-api:1.7.25"
                ],
                "file": "v1/https/jcenter.bintray.com/org/apache/httpcomponents/client5/httpclient5/5.0.3/httpclient5-5.0.3.jar",
                "mirror_urls": [
                    "https://jcenter.bintray.com/org/apache/httpcomponents/client5/httpclient5/5.0.3/httpclient5-5.0.3.jar"
                ],
                "sha256": "534574680bddf579a08a073981a10dd1f252e04ac4576f03f95b37ddd7042e4e",
                "url": "https://jcenter.bintray.com/org/apache/httpcomponents/client5/httpclient5/5.0.3/httpclient5-5.0.3.jar"
            },
            {
                "coord": "org.apache.httpcomponents.core5:httpcore5-h2:5.0.2",
                "dependencies": [
                    "org.apache.httpcomponents.core5:httpcore5:5.0.2"
                ],
                "directDependencies": [
                    "org.apache.httpcomponents.core5:httpcore5:5.0.2"
                ],
                "file": "v1/https/jcenter.bintray.com/org/apache/httpcomponents/core5/httpcore5-h2/5.0.2/httpcore5-h2-5.0.2.jar",
                "mirror_urls": [
                    "https://jcenter.bintray.com/org/apache/httpcomponents/core5/httpcore5-h2/5.0.2/httpcore5-h2-5.0.2.jar"
                ],
                "sha256": "49e88401c11c8b9f819b47b5c078077f713517b081a6093e4b0ff122db1d0ca4",
                "url": "https://jcenter.bintray.com/org/apache/httpcomponents/core5/httpcore5-h2/5.0.2/httpcore5-h2-5.0.2.jar"
            },
            {
                "coord": "org.apache.httpcomponents.core5:httpcore5:5.0.2",
                "dependencies": [],
                "directDependencies": [],
                "file": "v1/https/jcenter.bintray.com/org/apache/httpcomponents/core5/httpcore5/5.0.2/httpcore5-5.0.2.jar",
                "mirror_urls": [
                    "https://jcenter.bintray.com/org/apache/httpcomponents/core5/httpcore5/5.0.2/httpcore5-5.0.2.jar"
                ],
                "sha256": "1c645627a73511e1e297ab461921603eced3baa151e3b735faf4cecf429d11a5",
                "url": "https://jcenter.bintray.com/org/apache/httpcomponents/core5/httpcore5/5.0.2/httpcore5-5.0.2.jar"
            },
            {
                "coord": "org.checkerframework:checker-qual:2.5.2",
                "dependencies": [],
                "directDependencies": [],
                "file": "v1/https/jcenter.bintray.com/org/checkerframework/checker-qual/2.5.2/checker-qual-2.5.2.jar",
                "mirror_urls": [
                    "https://jcenter.bintray.com/org/checkerframework/checker-qual/2.5.2/checker-qual-2.5.2.jar"
                ],
                "sha256": "64b02691c8b9d4e7700f8ee2e742dce7ea2c6e81e662b7522c9ee3bf568c040a",
                "url": "https://jcenter.bintray.com/org/checkerframework/checker-qual/2.5.2/checker-qual-2.5.2.jar"
            },
            {
                "coord": "org.codehaus.mojo:animal-sniffer-annotations:1.17",
                "dependencies": [],
                "directDependencies": [],
                "file": "v1/https/jcenter.bintray.com/org/codehaus/mojo/animal-sniffer-annotations/1.17/animal-sniffer-annotations-1.17.jar",
                "mirror_urls": [
                    "https://jcenter.bintray.com/org/codehaus/mojo/animal-sniffer-annotations/1.17/animal-sniffer-annotations-1.17.jar"
                ],
                "sha256": "92654f493ecfec52082e76354f0ebf87648dc3d5cec2e3c3cdb947c016747a53",
                "url": "https://jcenter.bintray.com/org/codehaus/mojo/animal-sniffer-annotations/1.17/animal-sniffer-annotations-1.17.jar"
            },
            {
                "coord": "org.hamcrest:hamcrest-core:2.1",
                "dependencies": [
                    "org.hamcrest:hamcrest:2.1"
                ],
                "directDependencies": [
                    "org.hamcrest:hamcrest:2.1"
                ],
                "file": "v1/https/jcenter.bintray.com/org/hamcrest/hamcrest-core/2.1/hamcrest-core-2.1.jar",
                "mirror_urls": [
                    "https://jcenter.bintray.com/org/hamcrest/hamcrest-core/2.1/hamcrest-core-2.1.jar"
                ],
                "sha256": "e09109e54a289d88506b9bfec987ddd199f4217c9464132668351b9a4f00bee9",
                "url": "https://jcenter.bintray.com/org/hamcrest/hamcrest-core/2.1/hamcrest-core-2.1.jar"
            },
            {
                "coord": "org.hamcrest:hamcrest:2.1",
                "dependencies": [],
                "directDependencies": [],
                "file": "v1/https/jcenter.bintray.com/org/hamcrest/hamcrest/2.1/hamcrest-2.1.jar",
                "mirror_urls": [
                    "https://jcenter.bintray.com/org/hamcrest/hamcrest/2.1/hamcrest-2.1.jar"
                ],
                "sha256": "ba93b2e3a562322ba432f0a1b53addcc55cb188253319a020ed77f824e692050",
                "url": "https://jcenter.bintray.com/org/hamcrest/hamcrest/2.1/hamcrest-2.1.jar"
            },
            {
                "coord": "org.http4k:http4k-client-apache:3.284.0",
                "dependencies": [
                    "org.http4k:http4k-core:3.284.0",
                    "commons-codec:commons-codec:1.13",
                    "org.jetbrains.kotlin:kotlin-stdlib-common:1.4.21",
                    "org.apache.httpcomponents.core5:httpcore5:5.0.2",
                    "org.jetbrains.kotlin:kotlin-stdlib-jdk7:1.4.21",
                    "org.slf4j:slf4j-api:1.7.25",
                    "org.apache.httpcomponents.core5:httpcore5-h2:5.0.2",
                    "org.jetbrains.kotlin:kotlin-stdlib:1.4.21",
                    "org.apache.httpcomponents.client5:httpclient5:5.0.3",
                    "org.jetbrains:annotations:13.0",
                    "org.jetbrains.kotlin:kotlin-stdlib-jdk8:1.4.21"
                ],
                "directDependencies": [
                    "org.apache.httpcomponents.client5:httpclient5:5.0.3",
                    "org.http4k:http4k-core:3.284.0",
                    "org.jetbrains.kotlin:kotlin-stdlib-jdk8:1.4.21"
                ],
                "file": "v1/https/jcenter.bintray.com/org/http4k/http4k-client-apache/3.284.0/http4k-client-apache-3.284.0.jar",
                "mirror_urls": [
                    "https://jcenter.bintray.com/org/http4k/http4k-client-apache/3.284.0/http4k-client-apache-3.284.0.jar"
                ],
                "sha256": "94b143bdece028a74af1fb159b0fa416843d000dac824d247aee35f28e572045",
                "url": "https://jcenter.bintray.com/org/http4k/http4k-client-apache/3.284.0/http4k-client-apache-3.284.0.jar"
            },
            {
                "coord": "org.http4k:http4k-cloudnative:3.284.0",
                "dependencies": [
                    "org.http4k:http4k-core:3.284.0",
                    "org.jetbrains.kotlin:kotlin-stdlib-common:1.4.21",
                    "org.jetbrains.kotlin:kotlin-stdlib-jdk7:1.4.21",
                    "org.jetbrains.kotlin:kotlin-stdlib:1.4.21",
                    "org.jetbrains:annotations:13.0",
                    "org.jetbrains.kotlin:kotlin-stdlib-jdk8:1.4.21"
                ],
                "directDependencies": [
                    "org.http4k:http4k-core:3.284.0",
                    "org.jetbrains.kotlin:kotlin-stdlib-jdk8:1.4.21"
                ],
                "file": "v1/https/jcenter.bintray.com/org/http4k/http4k-cloudnative/3.284.0/http4k-cloudnative-3.284.0.jar",
                "mirror_urls": [
                    "https://jcenter.bintray.com/org/http4k/http4k-cloudnative/3.284.0/http4k-cloudnative-3.284.0.jar"
                ],
                "sha256": "49a46298646f90dca1128ea10b3c4c14be46df080a72015a3c16e510a630ea91",
                "url": "https://jcenter.bintray.com/org/http4k/http4k-cloudnative/3.284.0/http4k-cloudnative-3.284.0.jar"
            },
            {
                "coord": "org.http4k:http4k-core:3.284.0",
                "dependencies": [
                    "org.jetbrains.kotlin:kotlin-stdlib-common:1.4.21",
                    "org.jetbrains.kotlin:kotlin-stdlib-jdk7:1.4.21",
                    "org.jetbrains.kotlin:kotlin-stdlib:1.4.21",
                    "org.jetbrains:annotations:13.0",
                    "org.jetbrains.kotlin:kotlin-stdlib-jdk8:1.4.21"
                ],
                "directDependencies": [
                    "org.jetbrains.kotlin:kotlin-stdlib-jdk8:1.4.21"
                ],
                "file": "v1/https/jcenter.bintray.com/org/http4k/http4k-core/3.284.0/http4k-core-3.284.0.jar",
                "mirror_urls": [
                    "https://jcenter.bintray.com/org/http4k/http4k-core/3.284.0/http4k-core-3.284.0.jar"
                ],
                "sha256": "9eaec546528951bed1f9677cf564d2cfbe16eefacbdc48eebf4aea3af8e7dbfc",
                "url": "https://jcenter.bintray.com/org/http4k/http4k-core/3.284.0/http4k-core-3.284.0.jar"
            },
            {
                "coord": "org.http4k:http4k-format-core:3.284.0",
                "dependencies": [
                    "org.http4k:http4k-core:3.284.0",
                    "org.jetbrains.kotlin:kotlin-stdlib-common:1.4.21",
                    "org.jetbrains.kotlin:kotlin-stdlib-jdk7:1.4.21",
                    "org.jetbrains.kotlin:kotlin-stdlib:1.4.21",
                    "org.jetbrains:annotations:13.0",
                    "org.jetbrains.kotlin:kotlin-stdlib-jdk8:1.4.21"
                ],
                "directDependencies": [
                    "org.http4k:http4k-core:3.284.0",
                    "org.jetbrains.kotlin:kotlin-stdlib-jdk8:1.4.21"
                ],
                "file": "v1/https/jcenter.bintray.com/org/http4k/http4k-format-core/3.284.0/http4k-format-core-3.284.0.jar",
                "mirror_urls": [
                    "https://jcenter.bintray.com/org/http4k/http4k-format-core/3.284.0/http4k-format-core-3.284.0.jar"
                ],
                "sha256": "67e5df3bdb3eb352e9279f029404893407fa646dac14148eaeae0d480b239ff1",
                "url": "https://jcenter.bintray.com/org/http4k/http4k-format-core/3.284.0/http4k-format-core-3.284.0.jar"
            },
            {
                "coord": "org.http4k:http4k-format-jackson:3.284.0",
                "dependencies": [
                    "org.http4k:http4k-core:3.284.0",
                    "com.fasterxml.jackson.core:jackson-core:2.12.0",
                    "org.jetbrains.kotlin:kotlin-stdlib-common:1.4.21",
                    "org.jetbrains.kotlin:kotlin-stdlib-jdk7:1.4.21",
                    "org.http4k:http4k-format-core:3.284.0",
                    "com.fasterxml.jackson.core:jackson-databind:2.12.0",
                    "org.jetbrains.kotlin:kotlin-reflect:1.4.21",
                    "com.fasterxml.jackson.core:jackson-annotations:2.12.0",
                    "org.jetbrains.kotlin:kotlin-stdlib:1.4.21",
                    "org.jetbrains:annotations:13.0",
                    "com.fasterxml.jackson.module:jackson-module-kotlin:2.12.0",
                    "org.jetbrains.kotlin:kotlin-stdlib-jdk8:1.4.21"
                ],
                "directDependencies": [
                    "org.http4k:http4k-format-core:3.284.0",
                    "com.fasterxml.jackson.core:jackson-databind:2.12.0",
                    "org.jetbrains.kotlin:kotlin-reflect:1.4.21",
                    "com.fasterxml.jackson.module:jackson-module-kotlin:2.12.0",
                    "org.jetbrains.kotlin:kotlin-stdlib-jdk8:1.4.21"
                ],
                "file": "v1/https/jcenter.bintray.com/org/http4k/http4k-format-jackson/3.284.0/http4k-format-jackson-3.284.0.jar",
                "mirror_urls": [
                    "https://jcenter.bintray.com/org/http4k/http4k-format-jackson/3.284.0/http4k-format-jackson-3.284.0.jar"
                ],
                "sha256": "30f3279acbd387b9eaefca092f222f851fc067448dae6f59ca39ee3dc3e1dedb",
                "url": "https://jcenter.bintray.com/org/http4k/http4k-format-jackson/3.284.0/http4k-format-jackson-3.284.0.jar"
            },
            {
                "coord": "org.http4k:http4k-testing-servirtium:3.284.0",
                "dependencies": [
                    "org.http4k:http4k-core:3.284.0",
                    "commons-codec:commons-codec:1.13",
                    "com.fasterxml.jackson.core:jackson-core:2.12.0",
                    "org.jetbrains.kotlin:kotlin-stdlib-common:1.4.21",
                    "org.apache.httpcomponents.core5:httpcore5:5.0.2",
                    "org.jetbrains.kotlin:kotlin-stdlib-jdk7:1.4.21",
                    "org.slf4j:slf4j-api:1.7.25",
                    "org.http4k:http4k-format-core:3.284.0",
                    "org.apache.httpcomponents.core5:httpcore5-h2:5.0.2",
                    "org.http4k:http4k-format-jackson:3.284.0",
                    "com.fasterxml.jackson.core:jackson-databind:2.12.0",
                    "org.http4k:http4k-cloudnative:3.284.0",
                    "org.http4k:http4k-client-apache:3.284.0",
                    "org.jetbrains.kotlin:kotlin-reflect:1.4.21",
                    "com.fasterxml.jackson.core:jackson-annotations:2.12.0",
                    "org.jetbrains.kotlin:kotlin-stdlib:1.4.21",
                    "org.apache.httpcomponents.client5:httpclient5:5.0.3",
                    "org.jetbrains:annotations:13.0",
                    "com.fasterxml.jackson.module:jackson-module-kotlin:2.12.0",
                    "org.jetbrains.kotlin:kotlin-stdlib-jdk8:1.4.21"
                ],
                "directDependencies": [
                    "org.http4k:http4k-core:3.284.0",
                    "org.http4k:http4k-format-jackson:3.284.0",
                    "org.http4k:http4k-cloudnative:3.284.0",
                    "org.http4k:http4k-client-apache:3.284.0",
                    "org.jetbrains.kotlin:kotlin-stdlib-jdk8:1.4.21"
                ],
                "file": "v1/https/jcenter.bintray.com/org/http4k/http4k-testing-servirtium/3.284.0/http4k-testing-servirtium-3.284.0.jar",
                "mirror_urls": [
                    "https://jcenter.bintray.com/org/http4k/http4k-testing-servirtium/3.284.0/http4k-testing-servirtium-3.284.0.jar"
                ],
                "sha256": "1eafbacd7c676a2a8bb3855ac115d04d85317adde2323fb3b31cc78e289544fd",
                "url": "https://jcenter.bintray.com/org/http4k/http4k-testing-servirtium/3.284.0/http4k-testing-servirtium-3.284.0.jar"
            },
            {
                "coord": "org.jetbrains.kotlin:kotlin-reflect:1.4.21",
                "dependencies": [
                    "org.jetbrains.kotlin:kotlin-stdlib-common:1.4.21",
                    "org.jetbrains:annotations:13.0",
                    "org.jetbrains.kotlin:kotlin-stdlib:1.4.21"
                ],
                "directDependencies": [
                    "org.jetbrains.kotlin:kotlin-stdlib:1.4.21"
                ],
                "file": "v1/https/jcenter.bintray.com/org/jetbrains/kotlin/kotlin-reflect/1.4.21/kotlin-reflect-1.4.21.jar",
                "mirror_urls": [
                    "https://jcenter.bintray.com/org/jetbrains/kotlin/kotlin-reflect/1.4.21/kotlin-reflect-1.4.21.jar"
                ],
                "sha256": "7e1ae4f15a7aef746c5b89433f1c5e76b301a635854ef3c6b134b0ca31a36624",
                "url": "https://jcenter.bintray.com/org/jetbrains/kotlin/kotlin-reflect/1.4.21/kotlin-reflect-1.4.21.jar"
            },
            {
                "coord": "org.jetbrains.kotlin:kotlin-stdlib-common:1.4.21",
                "dependencies": [],
                "directDependencies": [],
                "file": "v1/https/jcenter.bintray.com/org/jetbrains/kotlin/kotlin-stdlib-common/1.4.21/kotlin-stdlib-common-1.4.21.jar",
                "mirror_urls": [
                    "https://jcenter.bintray.com/org/jetbrains/kotlin/kotlin-stdlib-common/1.4.21/kotlin-stdlib-common-1.4.21.jar"
                ],
                "sha256": "812cf197d9c4c67e1f47f95e2d72a9b600f0d1124560617bfe9850773eccbcff",
                "url": "https://jcenter.bintray.com/org/jetbrains/kotlin/kotlin-stdlib-common/1.4.21/kotlin-stdlib-common-1.4.21.jar"
            },
            {
                "coord": "org.jetbrains.kotlin:kotlin-stdlib-jdk7:1.4.21",
                "dependencies": [
                    "org.jetbrains.kotlin:kotlin-stdlib-common:1.4.21",
                    "org.jetbrains:annotations:13.0",
                    "org.jetbrains.kotlin:kotlin-stdlib:1.4.21"
                ],
                "directDependencies": [
                    "org.jetbrains.kotlin:kotlin-stdlib:1.4.21"
                ],
                "file": "v1/https/jcenter.bintray.com/org/jetbrains/kotlin/kotlin-stdlib-jdk7/1.4.21/kotlin-stdlib-jdk7-1.4.21.jar",
                "mirror_urls": [
                    "https://jcenter.bintray.com/org/jetbrains/kotlin/kotlin-stdlib-jdk7/1.4.21/kotlin-stdlib-jdk7-1.4.21.jar"
                ],
                "sha256": "50de5f7dad6235064ac6c0ff577f095a91b3306c2547d8bc372291587495024a",
                "url": "https://jcenter.bintray.com/org/jetbrains/kotlin/kotlin-stdlib-jdk7/1.4.21/kotlin-stdlib-jdk7-1.4.21.jar"
            },
            {
                "coord": "org.jetbrains.kotlin:kotlin-stdlib-jdk8:1.4.21",
                "dependencies": [
                    "org.jetbrains.kotlin:kotlin-stdlib-common:1.4.21",
                    "org.jetbrains:annotations:13.0",
                    "org.jetbrains.kotlin:kotlin-stdlib-jdk7:1.4.21",
                    "org.jetbrains.kotlin:kotlin-stdlib:1.4.21"
                ],
                "directDependencies": [
                    "org.jetbrains.kotlin:kotlin-stdlib:1.4.21",
                    "org.jetbrains.kotlin:kotlin-stdlib-jdk7:1.4.21"
                ],
                "file": "v1/https/jcenter.bintray.com/org/jetbrains/kotlin/kotlin-stdlib-jdk8/1.4.21/kotlin-stdlib-jdk8-1.4.21.jar",
                "mirror_urls": [
                    "https://jcenter.bintray.com/org/jetbrains/kotlin/kotlin-stdlib-jdk8/1.4.21/kotlin-stdlib-jdk8-1.4.21.jar"
                ],
                "sha256": "8ec3db1516948b2d3524e3afbe75cb5ac59e02d98cb6ef586ef57ba63ca8d11f",
                "url": "https://jcenter.bintray.com/org/jetbrains/kotlin/kotlin-stdlib-jdk8/1.4.21/kotlin-stdlib-jdk8-1.4.21.jar"
            },
            {
                "coord": "org.jetbrains.kotlin:kotlin-stdlib:1.4.21",
                "dependencies": [
                    "org.jetbrains.kotlin:kotlin-stdlib-common:1.4.21",
                    "org.jetbrains:annotations:13.0"
                ],
                "directDependencies": [
                    "org.jetbrains:annotations:13.0",
                    "org.jetbrains.kotlin:kotlin-stdlib-common:1.4.21"
                ],
                "file": "v1/https/jcenter.bintray.com/org/jetbrains/kotlin/kotlin-stdlib/1.4.21/kotlin-stdlib-1.4.21.jar",
                "mirror_urls": [
                    "https://jcenter.bintray.com/org/jetbrains/kotlin/kotlin-stdlib/1.4.21/kotlin-stdlib-1.4.21.jar"
                ],
                "sha256": "f78c5d8c09db985912ab83a1de3c3b53ddf208d7b151f06a72358ea3e137d01b",
                "url": "https://jcenter.bintray.com/org/jetbrains/kotlin/kotlin-stdlib/1.4.21/kotlin-stdlib-1.4.21.jar"
            },
            {
                "coord": "org.jetbrains:annotations:13.0",
                "dependencies": [],
                "directDependencies": [],
                "file": "v1/https/jcenter.bintray.com/org/jetbrains/annotations/13.0/annotations-13.0.jar",
                "mirror_urls": [
                    "https://jcenter.bintray.com/org/jetbrains/annotations/13.0/annotations-13.0.jar"
                ],
                "sha256": "ace2a10dc8e2d5fd34925ecac03e4988b2c0f851650c94b8cef49ba1bd111478",
                "url": "https://jcenter.bintray.com/org/jetbrains/annotations/13.0/annotations-13.0.jar"
            },
            {
                "coord": "org.slf4j:slf4j-api:1.7.25",
                "dependencies": [],
                "directDependencies": [],
                "file": "v1/https/jcenter.bintray.com/org/slf4j/slf4j-api/1.7.25/slf4j-api-1.7.25.jar",
                "mirror_urls": [
                    "https://jcenter.bintray.com/org/slf4j/slf4j-api/1.7.25/slf4j-api-1.7.25.jar"
                ],
                "sha256": "18c4a0095d5c1da6b817592e767bb23d29dd2f560ad74df75ff3961dbde25b79",
                "url": "https://jcenter.bintray.com/org/slf4j/slf4j-api/1.7.25/slf4j-api-1.7.25.jar"
            }
        ],
        "version": "0.1.0"
    }
}
